sqloader/__init__.py
sqloader/_prototype.py
sqloader/init.py
sqloader/migrator.py
sqloader/mysql.py
sqloader/sqlite3.py
sqloader/sqloader.py
sqloader-0.1.2.dist-info/licenses/LICENSE
sqloader-0.1.2.dist-info/METADATA
sqloader-0.1.2.dist-info/WHEEL
sqloader-0.1.2.dist-info/top_level.txt
sqloader-0.1.2.dist-info/RECORD
