Metadata-Version: 2.4
Name: sqloader
Version: 0.1.2
Summary: A simple and extensible SQL migration and loader utility for Python.
Home-page: https://github.com/horrible-gh/py_sqloader.git
Author: horrible-gh
Author-email: horrible <shinjpn1@gmail.com>
Project-URL: Homepage, https://github.com/horrible-gh/py_sqloader
Project-URL: Bug Tracker, https://github.com/horrible-gh/py_sqloader/issues
Keywords: sqloader,sql loader,migration,database migration,MySQL,SQLite,SQL migration,schema management,json sql loader
Classifier: Programming Language :: Python :: 3
Classifier: License :: OSI Approved :: MIT License
Classifier: Operating System :: OS Independent
Requires-Python: >=3.6
License-File: LICENSE
Requires-Dist: LogAssist
Requires-Dist: pymysql
Dynamic: author
Dynamic: home-page
Dynamic: license-file
Dynamic: requires-python
